business_id_nik/__init__.py
business_id_nik/business_id_nik.py
business_id_nik-0.93.1.dist-info/LICENSE
business_id_nik-0.93.1.dist-info/METADATA
business_id_nik-0.93.1.dist-info/WHEEL
business_id_nik-0.93.1.dist-info/top_level.txt
business_id_nik-0.93.1.dist-info/RECORD
